{
  "minecraft:recipes/building_blocks/mossy_cobblestone": {
    "criteria": {
      "has_vine": "2018-05-23 14:27:52 -0500"
    },
    "done": true
  },
  "minecraft:recipes/transportation/acacia_boat": {
    "criteria": {
      "entered_water": "2018-05-23 14:27:57 -0500"
    },
    "done": true
  },
  "minecraft:recipes/transportation/dark_oak_boat": {
    "criteria": {
      "entered_water": "2018-05-23 14:27:57 -0500"
    },
    "done": true
  },
  "minecraft:recipes/transportation/birch_boat": {
    "criteria": {
      "entered_water": "2018-05-23 14:27:57 -0500"
    },
    "done": true
  },
  "minecraft:recipes/transportation/boat": {
    "criteria": {
      "entered_water": "2018-05-23 14:27:57 -0500"
    },
    "done": true
  },
  "minecraft:recipes/transportation/jungle_boat": {
    "criteria": {
      "entered_water": "2018-05-23 14:27:57 -0500"
    },
    "done": true
  },
  "minecraft:recipes/transportation/spruce_boat": {
    "criteria": {
      "entered_water": "2018-05-23 14:27:57 -0500"
    },
    "done": true
  },
  "minecraft:recipes/misc/paper": {
    "criteria": {
      "has_reeds": "2018-05-23 14:27:53 -0500"
    },
    "done": true
  },
  "minecraft:recipes/misc/sugar": {
    "criteria": {
      "has_reeds": "2018-05-23 14:27:53 -0500"
    },
    "done": true
  },
  "minecraft:adventure/adventuring_time": {
    "criteria": {
      "forest": "2018-05-23 14:19:30 -0500",
      "swampland": "2018-05-23 14:23:34 -0500",
      "birch_forest": "2018-05-23 14:21:47 -0500",
      "plains": "2018-05-23 14:18:34 -0500",
      "birch_forest_hills": "2018-05-23 14:24:30 -0500",
      "river": "2018-05-23 14:20:20 -0500"
    },
    "done": false
  }
}